odoo8_addon_logistic_order-8.0.0.3.1-py2.7-nspkg.pth
odoo_addons/logistic_order/__openerp__.py
odoo_addons/logistic_order/__init__.py
odoo_addons/logistic_order/view/report_logisticorder.xml
odoo_addons/logistic_order/view/sale_order_view.xml
odoo_addons/logistic_order/i18n/logistic_order.pot
odoo_addons/logistic_order/i18n/en_US.po
odoo_addons/logistic_order/model/sale_order.py
odoo_addons/logistic_order/model/__init__.py
odoo_addons/logistic_order/test/test_report.yml
odoo_addons/logistic_order/data/logistic_order_sequence.xml
odoo_addons/logistic_order/workflow/sale_order.xml
odoo8_addon_logistic_order-8.0.0.3.1.dist-info/top_level.txt
odoo8_addon_logistic_order-8.0.0.3.1.dist-info/WHEEL
odoo8_addon_logistic_order-8.0.0.3.1.dist-info/RECORD
odoo8_addon_logistic_order-8.0.0.3.1.dist-info/metadata.json
odoo8_addon_logistic_order-8.0.0.3.1.dist-info/DESCRIPTION.rst
odoo8_addon_logistic_order-8.0.0.3.1.dist-info/METADATA
odoo8_addon_logistic_order-8.0.0.3.1.dist-info/namespace_packages.txt
