Metadata-Version: 2.0
Name: odoo8-addon-logistic-order
Version: 8.0.0.3.1
Summary: Sales Order as Logistics Order
Home-page: http://www.camptocamp.com
Author: UNKNOWN
Author-email: UNKNOWN
License: AGPL-3
Platform: UNKNOWN
Requires-Dist: odoo (<9.0a,>=8.0a)
Requires-Dist: odoo8-addon-sale-quotation-sourcing
Requires-Dist: odoo8-addon-sale-transport-multi-address
Requires-Dist: odoo8-addon-sale-validity
Classifier: Programming Language :: Python :: 2.7
Classifier: Framework :: Odoo
Classifier: License :: OSI Approved :: GNU Affero General Public License v3
